load_testing_data_selectionsort/create_chart.py
load_testing_data_selectionsort/generate_data.py
load_testing_data_selectionsort/load_testing_data/1_0.txt
load_testing_data_selectionsort/load_testing_data/1_1.txt
load_testing_data_selectionsort/load_testing_data/1_2.txt
load_testing_data_selectionsort/load_testing_data/1_3.txt
load_testing_data_selectionsort/load_testing_data/1_4.txt
load_testing_data_selectionsort/load_testing_data/2_0.txt
load_testing_data_selectionsort/load_testing_data/2_1.txt
load_testing_data_selectionsort/load_testing_data/2_2.txt
load_testing_data_selectionsort/load_testing_data/2_3.txt
load_testing_data_selectionsort/load_testing_data/2_4.txt
load_testing_data_selectionsort/load_testing_data/3_0.txt
load_testing_data_selectionsort/load_testing_data/3_1.txt
load_testing_data_selectionsort/load_testing_data/3_2.txt
load_testing_data_selectionsort/load_testing_data/3_3.txt
load_testing_data_selectionsort/load_testing_data/3_4.txt
load_testing_data_selectionsort/load_testing_data/4_0.txt
load_testing_data_selectionsort/load_testing_data/4_1.txt
load_testing_data_selectionsort/load_testing_data/4_2.txt
load_testing_data_selectionsort/load_testing_data/4_3.txt
load_testing_data_selectionsort/load_testing_data/4_4.txt
load_testing_data_selectionsort/load_testing_measurements/UNIX TIMESTAMP.csv
load_testing_data_selectionsort/load_testing_plots/UNIX TIMESTAMP.jpg
load_testing_data_selectionsort/measure_time.py
load_testing_data_selectionsort/selection_sort.py
load_testing_data_selectionsort-0.1.0.dist-info/entry_points.txt
load_testing_data_selectionsort-0.1.0.dist-info/WHEEL
load_testing_data_selectionsort-0.1.0.dist-info/METADATA
load_testing_data_selectionsort-0.1.0.dist-info/RECORD
